fastcrypter/__init__.py
fastcrypter/advanced_encryptor.py
fastcrypter/exceptions.py
fastcrypter/file_encryptor.py
fastcrypter/secure_compressor.py
fastcrypter/algorithms/__init__.py
fastcrypter/algorithms/compression/__init__.py
fastcrypter/algorithms/encryption/__init__.py
fastcrypter/core/__init__.py
fastcrypter/core/compressor.py
fastcrypter/core/custom_encoder.py
fastcrypter/core/encryptor.py
fastcrypter/core/enhanced_compressor.py
fastcrypter/core/key_manager.py
fastcrypter/utils/__init__.py
fastcrypter-2.3.6.dist-info/licenses/LICENSE
fastcrypter-2.3.6.dist-info/METADATA
fastcrypter-2.3.6.dist-info/WHEEL
fastcrypter-2.3.6.dist-info/entry_points.txt
fastcrypter-2.3.6.dist-info/top_level.txt
fastcrypter-2.3.6.dist-info/RECORD
