Metadata-Version: 2.4
Name: fastcrypter
Version: 2.3.6
Summary: Professional compression and encryption library with native C/C++ acceleration
Home-page: https://github.com/Pymmdrza/fastCrypter
Author: Mmdrza
Author-email: pymmdrza@gmail.com
Project-URL: Bug Reports, https://github.com/Pymmdrza/fastCrypter/issues
Project-URL: Source, https://github.com/Pymmdrza/fastCrypter
Project-URL: Documentation, https://fastCrypter.readthedocs.io/
Keywords: encryption,compression,security,cryptography,aes,chacha20,rsa,zlib,lzma,brotli,native,performance,c++,custom-encoding,fast
Classifier: Development Status :: 5 - Production/Stable
Classifier: Intended Audience :: Developers
Classifier: License :: OSI Approved :: MIT License
Classifier: Operating System :: OS Independent
Classifier: Programming Language :: Python :: 3
Classifier: Programming Language :: Python :: 3.8
Classifier: Programming Language :: Python :: 3.9
Classifier: Programming Language :: Python :: 3.10
Classifier: Programming Language :: Python :: 3.11
Classifier: Programming Language :: Python :: 3.12
Classifier: Topic :: Security :: Cryptography
Classifier: Topic :: System :: Archiving :: Compression
Classifier: Topic :: Software Development :: Libraries :: Python Modules
Requires-Python: >=3.8
License-File: LICENSE
Requires-Dist: cryptography
Requires-Dist: pycryptodome
Requires-Dist: brotli
Requires-Dist: argon2-cffi
Requires-Dist: bcrypt
Requires-Dist: numpy
Requires-Dist: cython
Requires-Dist: pytest
Requires-Dist: pytest-cov
Requires-Dist: pytest-benchmark
Requires-Dist: black
Requires-Dist: flake8
Requires-Dist: mypy
Requires-Dist: sphinx
Requires-Dist: sphinx-rtd-theme
Requires-Dist: psutil
Requires-Dist: tqdm
Provides-Extra: dev
Requires-Dist: pytest>=7.4.0; extra == "dev"
Requires-Dist: pytest-cov>=4.1.0; extra == "dev"
Requires-Dist: pytest-benchmark>=4.0.0; extra == "dev"
Requires-Dist: black>=23.0.0; extra == "dev"
Requires-Dist: flake8>=6.0.0; extra == "dev"
Requires-Dist: mypy>=1.5.0; extra == "dev"
Provides-Extra: docs
Requires-Dist: sphinx>=7.1.0; extra == "docs"
Requires-Dist: sphinx-rtd-theme>=1.3.0; extra == "docs"
Provides-Extra: native
Requires-Dist: numpy>=1.24.0; extra == "native"
Requires-Dist: cython>=3.0.0; extra == "native"
Dynamic: author
Dynamic: author-email
Dynamic: classifier
Dynamic: description
Dynamic: description-content-type
Dynamic: home-page
Dynamic: keywords
Dynamic: license-file
Dynamic: project-url
Dynamic: provides-extra
Dynamic: requires-dist
Dynamic: requires-python
Dynamic: summary
